README.rst
setup.py
auto_resizing_text_edit/__init__.py
auto_resizing_text_edit/auto_resizing_text_edit.py
auto_resizing_text_edit.egg-info/PKG-INFO
auto_resizing_text_edit.egg-info/SOURCES.txt
auto_resizing_text_edit.egg-info/dependency_links.txt
auto_resizing_text_edit.egg-info/top_level.txt
auto_resizing_text_edit/tests/__init__.py
auto_resizing_text_edit/tests/dummy_application.py
auto_resizing_text_edit/tests/test_auto_resizing_text_edit.py